hash_chunker/__init__.py
hash_chunker/hash_chunker.py
hash_chunker-0.1.9.dist-info/LICENSE
hash_chunker-0.1.9.dist-info/WHEEL
hash_chunker-0.1.9.dist-info/METADATA
hash_chunker-0.1.9.dist-info/RECORD
