Metadata-Version: 2.1
Name: hash-chunker
Version: 0.1.9
Summary: Generator that yields hash chunks for distributed data processing.
Home-page: https://github.com/whysage/hash_chunker
License: MIT
Author: Volodymyr Kochetkov
Author-email: whysages@gmail.com
Requires-Python: >=3.7,<4.0
Classifier: License :: OSI Approved :: MIT License
Classifier: Operating System :: OS Independent
Classifier: Programming Language :: Python :: 3
Classifier: Programming Language :: Python :: 3.7
Classifier: Programming Language :: Python :: 3.8
Classifier: Programming Language :: Python :: 3.9
Classifier: Programming Language :: Python :: 3.10
Classifier: Programming Language :: Python :: 3
Project-URL: Bug Tracker, https://github.com/whysage/hash_chunker/issues
Project-URL: Repository, https://github.com/whysage/hash_chunker
